oip_core_client/__init__.py
oip_core_client/converter.py
oip_core_client/dataset.py
oip_core_client/lib.py
oip_core_client/main.py
oip_core_client/retrieve.py
oip_core_client/schema.py
oip_core_client/units.py
oip_core_client-0.0.1.dist-info/METADATA
oip_core_client-0.0.1.dist-info/WHEEL
oip_core_client-0.0.1.dist-info/top_level.txt
oip_core_client-0.0.1.dist-info/RECORD
